shenzi/__init__.py
shenzi/bin/__init__.py
shenzi/bin/shenzi
shenzi/discover/__init__.py
shenzi/discover/callbacks.py
shenzi/discover/imports.py
shenzi/discover/intercept.py
shenzi/discover/monkeypatch.py
shenzi/discover/plat.py
shenzi/discover/python_props.py
shenzi/discover/types.py
shenzi/discover/all_libs/__init__.py
shenzi/discover/all_libs/macho.py
shenzi/discover/search/__init__.py
shenzi/discover/search/mac.py
shenzi/discover/search/linux/__init__.py
shenzi/discover/search/linux/ldconfig.py
shenzi/discover/search/linux/rpath.py
shenzi-0.0.4.dist-info/METADATA
shenzi-0.0.4.dist-info/WHEEL
shenzi-0.0.4.dist-info/entry_points.txt
shenzi-0.0.4.dist-info/RECORD
