Metadata-Version: 2.4
Name: shenzi
Version: 0.0.4
Summary: A greedy Python standalone application bundler
Project-URL: Repository, https://github.com/narang99/shenzi.git
Author-email: Hariom Narang <hariom2711@gmail.com>
Requires-Python: >=3.9
